Workbook

Sheet Dataset
A1: Order_ID | B1: Customer_Name | C1: Product_Category | D1: Product_Name | E1: Unit_Sold | F1: Unit_Price | G1: Discount_% | H1: Sales_Amount | I1: Order_Date | J1: City | K1: Segment | L1: Profit
A2: 1000 | B2: Brian Thompson | C2: Jeans | D2: Slim Fit Jeans | E2: 2 | F2: 842 | G2: 0.6 | H2: 0 | I2: 45715 | J2: Delhi | K2: B2C | L2: 2137.45
A3: 1001 | B3: Shaun Ross | C3: Jeans | D3: Slim Fit Jeans | E3: 1 | F3: 2747.545 | G3: 0.6 | H3: 0 | I3: 45853 | J3: Ahmedabad | K3: B2C | L3: 1588.15
A4: 1002 | B4: Sarah Snyder | C4: Jackets | D4: Puffer Coat | E4: 1 | F4: 637.82 | G4: 0.6 | H4: 0 | I4: 45659 | J4: Mumbai | K4: B2B | L4: -158.03
A5: 1003 | B5: Jay Briggs | C5: Shoes | D5: Loafers | E5: 2 | F5: 2962.27 | G5: 0.6 | H5: 0 | I5: 45826 | J5: Bengaluru | K5: B2B | L5: 2296.5
A6: 1004 | B6: Maria Blake | C6: Accessories | D6: Belts | E6: 1 | F6: 2881.07 | G6: 0.27 | H6: 2103.18 | I6: 45826 | J6: Hyderabad | K6: B2C | L6: 63.66
A7: 1005 | B7: Samuel Miller | C7: T-Shirts | D7: Crop Top | E7: 2 | F7: 2747.545 | G7: 0.6 | H7: 0 | I7: 45265 | J7: Mumbai | K7: B2B | L7: 1477.73
A8: 1006 | B8: John Mclean | C8: Jeans | D8: Boyfriend Jeans | E8: 1 | F8: 2060.85 | G8: 0.6 | H8: 0 | I8: 45384 | J8: Ahmedabad | K8: B2B | L8: 198.36
A9: 1007 | B9: Dr. Kathryn Bass PhD | C9: Dresses | D9: Casual Midi | E9: 2 | F9: 3669.56 | G9: 0.6 | H9: 0 | I9: 45826 | J9: Bengaluru | K9: B2C | L9: 2490.01
A10: 1008 | B10: Marie Fisher | C10: Accessories | D10: Sunglasses | E10: 2 | F10: 2747.545 | G10: 0.6 | H10: 0 | I10: 45826 | J10: Ahmedabad | K10: B2C | L10: -886.8
A11: 1009 | B11: Dale Perry | C11: T-Shirts | D11: Oversized T-shirt | E11: 5 | F11: 2747.545 | G11: 0.6 | H11: 0 | I11: 45858 | J11: Bengaluru | K11: B2B | L11: -972.73
A12: 1010 | B12: Oscar Turner | C12: T-Shirts | D12: Crop Top | E12: 0 | F12: 4007.02 | G12: 0.6 | H12: 0 | I12: 45826 | J12: Pune | K12: B2B | L12: -950.38
A13: 1011 | B13: Jacob Sanchez | C13: Accessories | D13: Belts | E13: 0 | F13: 2747.545 | G13: 0.6 | H13: 0 | I13: 45804 | J13: Delhi | K13: B2C | L13: 1370.67
... A502: 1500 | B502: Jerry Turner | C502: Jeans | D502: Straight Cut | E502: 2 | F502: 2128.74 | G502: 0.6 | H502: 0 | I502: 45588 | J502: Ahmedabad | K502: B2B | L502: -648.94

Sheet Day 13
A1: Order_ID | B1: Customer_Name | C1: Product_Category | D1: Product_Name | E1: Sales_Amount | F1: Profit
A2: 1000 | B2: =Observation!D20 -> 0 | C2: =VLOOKUP(A2,Dataset!A:L,3,FALSE) -> Jeans | D2: =VLOOKUP(A2,Dataset!A:L,4,FALSE) -> Slim Fit Jeans | E2: =VLOOKUP(A2,Dataset!A:L,8,FALSE) -> 0 | F2: =VLOOKUP(A2,Dataset!A:L,12,FALSE) -> 2137.45
A3: 1001 | B3: =VLOOKUP(A3,Dataset!A:L,2,FALSE) -> Shaun Ross | C3: =VLOOKUP(A3,Dataset!A:L,3,FALSE) -> Jeans | D3: =VLOOKUP(A3,Dataset!A:L,4,FALSE) -> Slim Fit Jeans | E3: =VLOOKUP(A3,Dataset!A:L,8,FALSE) -> 0 | F3: =VLOOKUP(A3,Dataset!A:L,12,FALSE) -> 1588.15
A4: 1002 | B4: =VLOOKUP(A4,Dataset!A:L,2,FALSE) -> Sarah Snyder | C4: =VLOOKUP(A4,Dataset!A:L,3,FALSE) -> Jackets | D4: =VLOOKUP(A4,Dataset!A:L,4,FALSE) -> Puffer Coat | E4: =VLOOKUP(A4,Dataset!A:L,8,FALSE) -> 0 | F4: =VLOOKUP(A4,Dataset!A:L,12,FALSE) -> -158.03
A5: 1003 | B5: =VLOOKUP(A5,Dataset!A:L,2,FALSE) -> Jay Briggs | C5: =VLOOKUP(A5,Dataset!A:L,3,FALSE) -> Shoes | D5: =VLOOKUP(A5,Dataset!A:L,4,FALSE) -> Loafers | E5: =VLOOKUP(A5,Dataset!A:L,8,FALSE) -> 0 | F5: =VLOOKUP(A5,Dataset!A:L,12,FALSE) -> 2296.5
A6: 1004 | B6: =VLOOKUP(A6,Dataset!A:L,2,FALSE) -> Maria Blake | C6: =VLOOKUP(A6,Dataset!A:L,3,FALSE) -> Accessories | D6: =VLOOKUP(A6,Dataset!A:L,4,FALSE) -> Belts | E6: =VLOOKUP(A6,Dataset!A:L,8,FALSE) -> 2103.18 | F6: =VLOOKUP(A6,Dataset!A:L,12,FALSE) -> 63.66
A7: 1005 | B7: =VLOOKUP(A7,Dataset!A:L,2,FALSE) -> Samuel Miller | C7: =VLOOKUP(A7,Dataset!A:L,3,FALSE) -> T-Shirts | D7: =VLOOKUP(A7,Dataset!A:L,4,FALSE) -> Crop Top | E7: =VLOOKUP(A7,Dataset!A:L,8,FALSE) -> 0 | F7: =VLOOKUP(A7,Dataset!A:L,12,FALSE) -> 1477.73
A8: 1006 | B8: =VLOOKUP(A8,Dataset!A:L,2,FALSE) -> John Mclean | C8: =VLOOKUP(A8,Dataset!A:L,3,FALSE) -> Jeans | D8: =VLOOKUP(A8,Dataset!A:L,4,FALSE) -> Boyfriend Jeans | E8: =VLOOKUP(A8,Dataset!A:L,8,FALSE) -> 0 | F8: =VLOOKUP(A8,Dataset!A:L,12,FALSE) -> 198.36
A9: 1007 | B9: =VLOOKUP(A9,Dataset!A:L,2,FALSE) -> Dr. Kathryn Bass PhD | C9: =VLOOKUP(A9,Dataset!A:L,3,FALSE) -> Dresses | D9: =VLOOKUP(A9,Dataset!A:L,4,FALSE) -> Casual Midi | E9: =VLOOKUP(A9,Dataset!A:L,8,FALSE) -> 0 | F9: =VLOOKUP(A9,Dataset!A:L,12,FALSE) -> 2490.01
A10: 1008 | B10: =VLOOKUP(A10,Dataset!A:L,2,FALSE) -> Marie Fisher | C10: =VLOOKUP(A10,Dataset!A:L,3,FALSE) -> Accessories | D10: =VLOOKUP(A10,Dataset!A:L,4,FALSE) -> Sunglasses | E10: =VLOOKUP(A10,Dataset!A:L,8,FALSE) -> 0 | F10: =VLOOKUP(A10,Dataset!A:L,12,FALSE) -> -886.8
A11: 1009 | B11: =VLOOKUP(A11,Dataset!A:L,2,FALSE) -> Dale Perry | C11: =VLOOKUP(A11,Dataset!A:L,3,FALSE) -> T-Shirts | D11: =VLOOKUP(A11,Dataset!A:L,4,FALSE) -> Oversized T-shirt | E11: =VLOOKUP(A11,Dataset!A:L,8,FALSE) -> 0 | F11: =VLOOKUP(A11,Dataset!A:L,12,FALSE) -> -972.73
A12: 1010 | B12: =VLOOKUP(A12,Dataset!A:L,2,FALSE) -> Oscar Turner | C12: =VLOOKUP(A12,Dataset!A:L,3,FALSE) -> T-Shirts | D12: =VLOOKUP(A12,Dataset!A:L,4,FALSE) -> Crop Top | E12: =VLOOKUP(A12,Dataset!A:L,8,FALSE) -> 0 | F12: =VLOOKUP(A12,Dataset!A:L,12,FALSE) -> -950.38
A13: 1011 | B13: =VLOOKUP(A13,Dataset!A:L,2,FALSE) -> Jacob Sanchez | C13: =VLOOKUP(A13,Dataset!A:L,3,FALSE) -> Accessories | D13: =VLOOKUP(A13,Dataset!A:L,4,FALSE) -> Belts | E13: =VLOOKUP(A13,Dataset!A:L,8,FALSE) -> 0 | F13: =VLOOKUP(A13,Dataset!A:L,12,FALSE) -> 1370.67
A14: 1012 | B14: =VLOOKUP(A14,Dataset!A:L,2,FALSE) -> Valerie Hampton | C14: =VLOOKUP(A14,Dataset!A:L,3,FALSE) -> Jeans | D14: =VLOOKUP(A14,Dataset!A:L,4,FALSE) -> Straight Cut | E14: =VLOOKUP(A14,Dataset!A:L,8,FALSE) -> 0 | F14: =VLOOKUP(A14,Dataset!A:L,12,FALSE) -> 843.61
... A502: 1500 | B502: =VLOOKUP(A502,Dataset!A:L,2,FALSE) -> Jerry Turner | C502: =VLOOKUP(A502,Dataset!A:L,3,FALSE) -> Jeans | D502: =VLOOKUP(A502,Dataset!A:L,4,FALSE) -> Straight Cut | E502: =VLOOKUP(A502,Dataset!A:L,8,FALSE) -> 0 | F502: =VLOOKUP(A502,Dataset!A:L,12,FALSE) -> -648.94

Sheet Observation
A1: OBSERVATION
A2: Day 13 – Lookup & Reference Functions (Part 1), the task is to duplicate the dataset using the VLOOKUP() function.
A4: 1.VLOOKUP searches for a value in the first column of a table.
A5: 2.It retrieves matching data from another column.
A6: 3.The Order ID is used as the lookup value.
A7: 4.The duplicated dataset matches the original dataset.
A8: 5.VLOOKUP saves time by automatically fetching data Using this =VLOOKUP(A2,Dataset!A:L,2,FALSE)
A9: 6.It reduces manual data entry errors.
A10: 7.Using FALSE returns an exact match.
A11: 8.The formula can be copied down to retrieve all records.
A12: 9.VLOOKUP is useful for combining data from different tables.
A13: 10.Overall, VLOOKUP makes data retrieval fast and accurate.
